{
  "project_info": {
    "project_number": "293245531607",
    "project_id": "logbaseretr",
    "storage_bucket": "logbaseretr.appspot.com"
  },
  "client": [
    {
      "client_info": {
        "mobilesdk_app_id": "1:293245531607:android:3f8cb34a91d23a2382c792",
        "android_client_info": {
          "package_name": "com.example.myapplication"
        }
      },
      "oauth_client": [],
      "api_key": [
        {
          "current_key": "AIzaSyA-t7Fke9YXFkP0Rwf94m4lKyMNPFb8P04"
        }
      ],
      "services": {
        "appinvite_service": {
          "other_platform_oauth_client": []
        }
      }
    }
  ],
  "configuration_version": "1"
}